{
  "name": "Tailwind Lime Light",
  "type": "light",
  "colors": {
    "editor.background": "#f7fee7",
    "editor.foreground": "#3f6212",
    "editorCursor.foreground": "#65a30d",
    "editor.lineHighlightBackground": "#ecfccb",
    "editor.selectionBackground": "#d9f99d",
    "editor.selectionHighlightBackground": "#d9f99d",
    "editor.wordHighlightBackground": "#d9f99d",
    "editor.wordHighlightStrongBackground": "#d9f99d",
    "editor.findMatchBackground": "#bef264",
    "editor.findMatchHighlightBackground": "#d9f99d",
    "editor.hoverHighlightBackground": "#ecfccb",
    "editorLineNumber.foreground": "#a3e635",
    "editorLineNumber.activeForeground": "#65a30d",
    "editorIndentGuide.background": "#d9f99d",
    "editorIndentGuide.activeBackground": "#a3e635",
    "editorWhitespace.foreground": "#bef264",
    "editorRuler.foreground": "#d9f99d",
    "activityBar.background": "#ecfccb",
    "activityBar.foreground": "#4d7c0f",
    "activityBar.activeBorder": "#84cc16",
    "activityBarBadge.background": "#84cc16",
    "activityBarBadge.foreground": "#f7fee7",
    "sideBar.background": "#ecfccb",
    "sideBar.foreground": "#4d7c0f",
    "sideBarTitle.foreground": "#3f6212",
    "sideBarSectionHeader.background": "#d9f99d",
    "sideBarSectionHeader.foreground": "#3f6212",
    "statusBar.background": "#65a30d",
    "statusBar.foreground": "#f7fee7",
    "statusBar.debuggingBackground": "#dc2626",
    "statusBar.debuggingForeground": "#fef2f2",
    "statusBar.noFolderBackground": "#84cc16",
    "tab.activeBackground": "#f7fee7",
    "tab.activeForeground": "#3f6212",
    "tab.inactiveBackground": "#ecfccb",
    "tab.inactiveForeground": "#65a30d",
    "tab.border": "#d9f99d",
    "tab.activeBorder": "#84cc16",
    "panel.background": "#ecfccb",
    "panel.border": "#d9f99d",
    "panelTitle.activeForeground": "#3f6212",
    "panelTitle.inactiveForeground": "#65a30d",
    "terminal.background": "#f7fee7",
    "terminal.foreground": "#3f6212",
    "terminal.ansiBlack": "#365314",
    "terminal.ansiRed": "#ef4444",
    "terminal.ansiGreen": "#22c55e",
    "terminal.ansiYellow": "#eab308",
    "terminal.ansiBlue": "#3b82f6",
    "terminal.ansiMagenta": "#a855f7",
    "terminal.ansiCyan": "#06b6d4",
    "terminal.ansiWhite": "#ecfccb",
    "button.background": "#84cc16",
    "button.foreground": "#f7fee7",
    "button.hoverBackground": "#65a30d",
    "input.background": "#f7fee7",
    "input.foreground": "#3f6212",
    "input.border": "#bef264",
    "inputOption.activeBorder": "#84cc16",
    "dropdown.background": "#f7fee7",
    "dropdown.foreground": "#3f6212",
    "dropdown.border": "#bef264",
    "list.activeSelectionBackground": "#d9f99d",
    "list.activeSelectionForeground": "#3f6212",
    "list.hoverBackground": "#ecfccb",
    "list.inactiveSelectionBackground": "#ecfccb",
    "list.focusBackground": "#d9f99d",
    "scrollbar.shadow": "#d9f99d",
    "scrollbarSlider.background": "#bef264",
    "scrollbarSlider.hoverBackground": "#a3e635",
    "scrollbarSlider.activeBackground": "#84cc16",
    "badge.background": "#84cc16",
    "badge.foreground": "#f7fee7",
    "progressBar.background": "#84cc16",
    "window.activeBorder": "#bef264",
    "window.inactiveBorder": "#d9f99d"
  },
  "tokenColors": [
    {
      "name": "Comment",
      "scope": [
        "comment",
        "punctuation.definition.comment"
      ],
      "settings": {
        "fontStyle": "italic",
        "foreground": "#84cc16"
      }
    },
    {
      "name": "Variables",
      "scope": [
        "variable",
        "string constant.other.placeholder"
      ],
      "settings": {
        "foreground": "#4d7c0f"
      }
    },
    {
      "name": "Keywords",
      "scope": [
        "keyword",
        "storage.type",
        "storage.modifier"
      ],
      "settings": {
        "foreground": "#9333ea"
      }
    },
    {
      "name": "Operators",
      "scope": "keyword.operator",
      "settings": {
        "foreground": "#db2777"
      }
    },
    {
      "name": "Strings",
      "scope": [
        "string",
        "string.quoted"
      ],
      "settings": {
        "foreground": "#16a34a"
      }
    },
    {
      "name": "Functions",
      "scope": [
        "entity.name.function",
        "meta.require",
        "support.function.any-method"
      ],
      "settings": {
        "foreground": "#2563eb"
      }
    },
    {
      "name": "Classes",
      "scope": [
        "entity.name.type",
        "entity.other.inherited-class",
        "support.class"
      ],
      "settings": {
        "foreground": "#a16207"
      }
    },
    {
      "name": "Numbers",
      "scope": [
        "constant.numeric",
        "constant.language",
        "support.constant",
        "constant.character.escape"
      ],
      "settings": {
        "foreground": "#ea580c"
      }
    },
    {
      "name": "Tags",
      "scope": [
        "entity.name.tag",
        "markup.deleted.git_gutter"
      ],
      "settings": {
        "foreground": "#dc2626"
      }
    },
    {
      "name": "Attributes",
      "scope": [
        "entity.other.attribute-name"
      ],
      "settings": {
        "foreground": "#ea580c"
      }
    }
  ]
}